{
 "name" : "WindVelocityProfile",
 "type" : "core:Blueprint",
 "extends" : ["sima:sima/MOAO"],
 "attributes" : [{
   "name" : "verticalCoordinate",
   "type" : "core:BlueprintAttribute",
   "attributeType" : "number",
   "description" : "Vertical coordinate of profile level",
   "optional" : true
  }, {
   "name" : "longitudinalVelocityFactor",
   "type" : "core:BlueprintAttribute",
   "attributeType" : "number",
   "description" : "Wind speed scaling factor for fluctuating part of the longitudinal wind",
   "optional" : true
  }, {
   "name" : "lateralVelocityFactor",
   "type" : "core:BlueprintAttribute",
   "attributeType" : "number",
   "description" : "Wind speed scaling factor for the lateral wind velocity",
   "optional" : true
  }, {
   "name" : "verticalVelocityFactor",
   "type" : "core:BlueprintAttribute",
   "attributeType" : "number",
   "description" : "Wind speed scaling factor for the vertical wind velocity",
   "optional" : true
  }]
}
