{
 "name" : "InitialCondition",
 "type" : "core:Blueprint",
 "extends" : ["sima:sima/Condition", "sima:sima/NamedObject"],
 "attributes" : [{
   "name" : "changeNumber",
   "type" : "core:BlueprintAttribute",
   "attributeType" : "integer",
   "optional" : true
  }, {
   "name" : "resultContainer",
   "type" : "core:BlueprintAttribute",
   "attributeType" : "sima:sima/ResultContainer",
   "contained" : true,
   "optional" : true
  }, {
   "name" : "name",
   "type" : "core:BlueprintAttribute",
   "attributeType" : "string",
   "optional" : true
  }]
}
