{
 "name" : "CoordinateSystemTransform",
 "type" : "core:Blueprint",
 "extends" : ["./OperationNode"],
 "attributes" : [{
   "name" : "x",
   "type" : "core:BlueprintAttribute",
   "attributeType" : "integer",
   "optional" : true
  }, {
   "name" : "y",
   "type" : "core:BlueprintAttribute",
   "attributeType" : "integer",
   "optional" : true
  }, {
   "name" : "name",
   "type" : "core:BlueprintAttribute",
   "attributeType" : "string",
   "optional" : true
  }, {
   "name" : "h",
   "type" : "core:BlueprintAttribute",
   "attributeType" : "integer",
   "optional" : true
  }, {
   "name" : "w",
   "type" : "core:BlueprintAttribute",
   "attributeType" : "integer",
   "optional" : true
  }, {
   "name" : "controlSignalInputSlots",
   "type" : "core:BlueprintAttribute",
   "attributeType" : "./ControlSignalInputSlot",
   "dimensions" : "*",
   "contained" : true,
   "optional" : true
  }, {
   "name" : "filterInputSlots",
   "type" : "core:BlueprintAttribute",
   "attributeType" : "./InputSlot",
   "dimensions" : "*",
   "contained" : true,
   "optional" : true
  }, {
   "name" : "filterOutputSlots",
   "type" : "core:BlueprintAttribute",
   "attributeType" : "./OutputSlot",
   "dimensions" : "*",
   "contained" : true,
   "optional" : true
  }, {
   "name" : "inputCoordinateSystem",
   "type" : "core:BlueprintAttribute",
   "attributeType" : "boolean",
   "description" : "Specify the reference coordinate system by passing in a 3 or 6 dof position signal or a 9 dof rotation matrix (row order)",
   "optional" : true
  }, {
   "name" : "offsetX",
   "type" : "core:BlueprintAttribute",
   "attributeType" : "number",
   "optional" : true
  }, {
   "name" : "offsetY",
   "type" : "core:BlueprintAttribute",
   "attributeType" : "number",
   "optional" : true
  }, {
   "name" : "offsetZ",
   "type" : "core:BlueprintAttribute",
   "attributeType" : "number",
   "optional" : true
  }, {
   "name" : "rotationX",
   "type" : "core:BlueprintAttribute",
   "attributeType" : "number",
   "optional" : true
  }, {
   "name" : "rotationY",
   "type" : "core:BlueprintAttribute",
   "attributeType" : "number",
   "optional" : true
  }, {
   "name" : "rotationZ",
   "type" : "core:BlueprintAttribute",
   "attributeType" : "number",
   "optional" : true
  }]
}
