{
 "name" : "BiasBladePitchFaultItem",
 "type" : "system/SIMOS/Blueprint",
 "abstract" : false,
 "extends" : ["system/SIMOS/NamedEntity"],
 "attributes" : [{
   "name" : "startTime",
   "type" : "system/SIMOS/BlueprintAttribute",
   "attributeType" : "number",
   "description" : "Start time for blade pitch fault",
   "default" : "0.0"
  }, {
   "name" : "line",
   "type" : "system/SIMOS/BlueprintAttribute",
   "attributeType" : "/riflex/ARLine",
   "contained" : false,
   "optional" : true
  }, {
   "name" : "pitchDeviation",
   "type" : "system/SIMOS/BlueprintAttribute",
   "attributeType" : "number",
   "description" : "Pitch deviation from required pitch",
   "default" : "0.0"
  }, {
   "name" : "rampDuration",
   "type" : "system/SIMOS/BlueprintAttribute",
   "attributeType" : "number",
   "description" : "Ramp duration to full pitch deviation",
   "default" : "0.0"
  }],
 "storageRecipes" : [],
 "uiRecipes" : []
}

