{
 "name" : "BladeItem",
 "type" : "core:Blueprint",
 "abstract" : false,
 "extends" : ["/sima/MOAO"],
 "attributes" : [{
   "name" : "eccentricityLine",
   "type" : "core:BlueprintAttribute",
   "attributeType" : "/riflex/ARLine",
   "contained" : false,
   "optional" : true
  }, {
   "name" : "bladeLine",
   "type" : "core:BlueprintAttribute",
   "attributeType" : "/riflex/ARLine",
   "contained" : false,
   "optional" : true
  }],
 "storageRecipes" : [],
 "uiRecipes" : []
}

