{
 "name" : "HLAPipeRoute",
 "type" : "core:Blueprint",
 "abstract" : false,
 "extends" : ["/hla/HLAObject"],
 "attributes" : [{
   "name" : "name",
   "type" : "core:BlueprintAttribute",
   "attributeType" : "string",
   "optional" : true
  }, {
   "name" : "routeFile",
   "type" : "core:BlueprintAttribute",
   "attributeType" : "string",
   "optional" : true
  }, {
   "name" : "coordsUTM",
   "type" : "core:BlueprintAttribute",
   "attributeType" : "string",
   "optional" : true,
   "default" : "no"
  }, {
   "name" : "mapOnTerrain",
   "type" : "core:BlueprintAttribute",
   "attributeType" : "string",
   "optional" : true,
   "default" : "auto"
  }, {
   "name" : "routeWidth",
   "type" : "core:BlueprintAttribute",
   "attributeType" : "number",
   "optional" : true
  }, {
   "name" : "color",
   "type" : "core:BlueprintAttribute",
   "attributeType" : "/sima/SIMAColor",
   "contained" : false,
   "optional" : true
  }, {
   "name" : "routeWidthColor",
   "type" : "core:BlueprintAttribute",
   "attributeType" : "/sima/SIMAColor",
   "contained" : false,
   "optional" : true
  }],
 "storageRecipes" : [],
 "uiRecipes" : []
}
