{
 "name" : "TurbulenceBoxScaling",
 "type" : "system/SIMOS/Blueprint",
 "abstract" : false,
 "extends" : ["/sima/MOAO"],
 "attributes" : [{
   "name" : "scalingOption",
   "type" : "system/SIMOS/BlueprintAttribute",
   "attributeType" : "string",
   "enumType" : "/windpark/ScalingOption",
   "optional" : true,
   "default" : "NONE"
  }, {
   "name" : "windDirectionScalingFactor",
   "type" : "system/SIMOS/BlueprintAttribute",
   "attributeType" : "number",
   "optional" : true,
   "default" : "1.0"
  }, {
   "name" : "transverseDirectionScalingFactor",
   "type" : "system/SIMOS/BlueprintAttribute",
   "attributeType" : "number",
   "optional" : true,
   "default" : "0.8"
  }, {
   "name" : "verticalDirectionScalingFactor",
   "type" : "system/SIMOS/BlueprintAttribute",
   "attributeType" : "number",
   "optional" : true,
   "default" : "0.5"
  }],
 "storageRecipes" : [],
 "uiRecipes" : []
}

