{
 "name" : "HydrostaticStiffnessData",
 "type" : "core:Blueprint",
 "abstract" : false,
 "extends" : ["/sima/MOAO"],
 "attributes" : [{
   "name" : "matrix",
   "type" : "core:BlueprintAttribute",
   "attributeType" : "/hydro/HydrostaticStiffnessMatrix",
   "contained" : true,
   "optional" : false
  }, {
   "name" : "reference",
   "type" : "core:BlueprintAttribute",
   "attributeType" : "/sima/Position",
   "contained" : true,
   "optional" : false
  }],
 "storageRecipes" : [],
 "uiRecipes" : []
}
