{
 "name" : "TimeSimulationResult",
 "type" : "system/SIMOS/Blueprint",
 "abstract" : false,
 "extends" : ["/sima/Result"],
 "attributes" : [{
   "name" : "properties",
   "type" : "system/SIMOS/BlueprintAttribute",
   "attributeType" : "/sima/Property",
   "dimensions" : "*",
   "contained" : true,
   "optional" : true
  }, {
   "name" : "resource",
   "type" : "system/SIMOS/BlueprintAttribute",
   "attributeType" : "string",
   "optional" : true
  }, {
   "name" : "relative",
   "type" : "system/SIMOS/BlueprintAttribute",
   "attributeType" : "boolean",
   "optional" : true
  }, {
   "name" : "name",
   "type" : "system/SIMOS/BlueprintAttribute",
   "attributeType" : "string",
   "optional" : true
  }, {
   "name" : "_type",
   "type" : "system/SIMOS/BlueprintAttribute",
   "attributeType" : "string",
   "optional" : true
  }, {
   "name" : "time",
   "type" : "system/SIMOS/BlueprintAttribute",
   "attributeType" : "integer",
   "optional" : true,
   "default" : "-1"
  }, {
   "name" : "size",
   "type" : "system/SIMOS/BlueprintAttribute",
   "attributeType" : "integer",
   "optional" : true,
   "default" : "-1"
  }, {
   "name" : "runNumber",
   "type" : "system/SIMOS/BlueprintAttribute",
   "attributeType" : "integer",
   "optional" : true,
   "default" : "-1"
  }, {
   "name" : "messages",
   "type" : "system/SIMOS/BlueprintAttribute",
   "attributeType" : "/sima/SimaMessage",
   "dimensions" : "*",
   "contained" : true,
   "optional" : true
  }],
 "storageRecipes" : [],
 "uiRecipes" : []
}

