{
 "name" : "Workflow",
 "type" : "core:Blueprint",
 "abstract" : false,
 "extends" : ["/sima/NamedObject"],
 "attributes" : [{
   "name" : "nodes",
   "type" : "core:BlueprintAttribute",
   "attributeType" : "/post/RunNode",
   "dimensions" : "*",
   "contained" : true,
   "optional" : true
  }, {
   "name" : "connections",
   "type" : "core:BlueprintAttribute",
   "attributeType" : "/post/SlotConnection",
   "dimensions" : "*",
   "contained" : true,
   "optional" : true
  }, {
   "name" : "name",
   "type" : "core:BlueprintAttribute",
   "attributeType" : "string",
   "optional" : true
  }, {
   "name" : "computeServiceID",
   "type" : "core:BlueprintAttribute",
   "attributeType" : "string",
   "optional" : true
  }],
 "storageRecipes" : [],
 "uiRecipes" : []
}

