{
 "name" : "DirectionDependentWeibullDistribution",
 "type" : "core:Blueprint",
 "abstract" : false,
 "extends" : ["/metocean/WeibullDistribution"],
 "attributes" : [{
   "name" : "name",
   "type" : "core:BlueprintAttribute",
   "attributeType" : "string",
   "optional" : true
  }, {
   "name" : "returnPeriod",
   "type" : "core:BlueprintAttribute",
   "attributeType" : "number",
   "optional" : true
  }, {
   "name" : "level",
   "type" : "core:BlueprintAttribute",
   "attributeType" : "number",
   "optional" : true
  }, {
   "name" : "duration",
   "type" : "core:BlueprintAttribute",
   "attributeType" : "number",
   "optional" : true,
   "default" : "0.0"
  }, {
   "name" : "items",
   "type" : "core:BlueprintAttribute",
   "attributeType" : "/metocean/WeibullDistributionItem",
   "dimensions" : "*",
   "contained" : true,
   "optional" : true
  }],
 "storageRecipes" : [],
 "uiRecipes" : []
}

